waterdip/__init__.py
waterdip/version.py
waterdip-0.1.0.dist-info/WHEEL
waterdip-0.1.0.dist-info/METADATA
waterdip-0.1.0.dist-info/RECORD
