Metadata-Version: 2.1
Name: waterdip
Version: 0.1.0
Summary: Waterdip Python SDK
Author: Subhankar
Author-email: suhankar@waterdip.ai
Requires-Python: >=3.7,<4.0
Classifier: Programming Language :: Python :: 3
Classifier: Programming Language :: Python :: 3.7
Classifier: Programming Language :: Python :: 3.8
